{
    "1966100": {
        "playerItemId": "1966100",
        "buddyItemId": "",
        "replica": {
            "baseRecord": "records\/items\/gearweapons\/focus\/c008_focus.dbr",
            "prefixRecord": "",
            "suffixRecord": "",
            "modifierRecord": "",
            "transmuteRecord": "",
            "seed": "1132452469",
            "materiaRecord": "",
            "relicBonus": "",
            "relicSeed": "0",
            "enchantmentRecord": "",
            "enchantmentSeed": "0"
        },
        "stats": [
            {
                "text": "^Bтёмный гримуар Ог'Напеша",
                "type": "5"
            },
            {
                "text": "\"Тёмные записи Ог'Напеша, осуждённого некроманта\"",
                "type": "16"
            },
            {
                "text": "Эпические тотемы\/книги",
                "type": "64"
            },
            {
                "text": " ",
                "type": "0"
            },
            {
                "text": "+56% ^Mурона здоровью^E",
                "type": "18"
            },
            {
                "text": "+19 ^Fдуха^E",
                "type": "18"
            },
            {
                "text": "+23 ^Xнавыка атаки^E",
                "type": "18"
            },
            {
                "text": "+3.8 ^Eэнергии в сек.",
                "type": "18"
            },
            {
                "text": "+9% ^Xскорости колдовства^E",
                "type": "18"
            },
            {
                "text": "-15% ^Eвремени перезарядки умения",
                "type": "18"
            },
            {
                "text": "+2 к умению Урожай душ (Некромант)",
                "type": "79"
            },
            {
                "text": " ",
                "type": "0"
            },
            {
                "text": "Бонус всем питомцам",
                "type": "68"
            },
            {
                "text": "+17% ^Xобщего урона^E",
                "type": "69"
            },
            {
                "text": "+6% ^Xобщей скорости^E",
                "type": "69"
            },
            {
                "text": " ",
                "type": "0"
            },
            {
                "text": "Дарованные умения",
                "type": "34"
            },
            {
                "text": "Дух Ог'Напеша (Добавлено предметом)",
                "type": "35"
            },
            {
                "text": "Чтение тёмных трудов Ог'Напеша поможет вызвать его самое страшное проявление обратно в мир живых. ^oТолько один Дух может быть призван за раз. Дух получает все бонусы питомцев.",
                "type": "37"
            },
            {
                "text": " ",
                "type": "0"
            },
            {
                "text": "180 ^Eзатраты энергии",
                "type": "18"
            },
            {
                "text": "30 ^Eсек. ^Eперезарядка умения",
                "type": "18"
            },
            {
                "text": " ",
                "type": "0"
            },
            {
                "text": "17969 ^Eздоровье",
                "type": "40"
            },
            {
                "text": "1549 ^Eэнергия",
                "type": "40"
            },
            {
                "text": " ",
                "type": "0"
            },
            {
                "text": "Умения  ^AДух Ог'Напеша:",
                "type": "23"
            },
            {
                "text": "237-550 ^Kфизического урона^E",
                "type": "40"
            },
            {
                "text": "133 ^Oурона огнём^E",
                "type": "40"
            },
            {
                "text": " ",
                "type": "0"
            },
            {
                "text": "Нужно: 40 Уровень игрока",
                "type": "19"
            },
            {
                "text": "Нужно: 400 Дух",
                "type": "19"
            }
        ]
    }
}
