{
    "1736727": {
        "playerItemId": "1736727",
        "buddyItemId": "",
        "replica": {
            "baseRecord": "records\/items\/gearweapons\/blunt1h\/a09_blunt002.dbr",
            "prefixRecord": "records\/items\/lootaffixes\/prefix\/ao014b_vitality_06.dbr",
            "suffixRecord": "records\/items\/lootaffixes\/suffix\/b_wpn012_melee1h_d.dbr",
            "modifierRecord": "",
            "transmuteRecord": "",
            "seed": "35856745",
            "materiaRecord": "",
            "relicBonus": "",
            "relicSeed": "0",
            "enchantmentRecord": "",
            "enchantmentSeed": "0"
        },
        "stats": [
            {
                "text": "^yразлагающий ^sштурмовой ^Wклевец ^gзвериной ярости",
                "type": "4"
            },
            {
                "text": "Редкая одноручная булава",
                "type": "64"
            },
            {
                "text": "17-178 ^Kфизического урона^S",
                "type": "17"
            },
            {
                "text": "^W1.74 ^Sатак в сек.",
                "type": "19"
            },
            {
                "text": " ",
                "type": "0"
            },
            {
                "text": "19 ^Mурона здоровью^E",
                "type": "18"
            },
            {
                "text": "16% конверсия: ^E^Kфизический урон^E в ^Mурон здоровью^E",
                "type": "18"
            },
            {
                "text": "+195 ^Fздоровья^E",
                "type": "18"
            },
            {
                "text": "+33 ^Xнавыка атаки^E",
                "type": "18"
            },
            {
                "text": "+3 к умению Призыв шипастого зверя (Шаман)",
                "type": "79"
            },
            {
                "text": " ",
                "type": "0"
            },
            {
                "text": "Бонус всем питомцам",
                "type": "68"
            },
            {
                "text": "+23% ^Xобщего урона^E",
                "type": "69"
            },
            {
                "text": "+13% ^Xскорости атаки^E",
                "type": "69"
            },
            {
                "text": " ",
                "type": "0"
            },
            {
                "text": "Нужно: 56 Уровень игрока",
                "type": "19"
            },
            {
                "text": "Нужно: 377 Телосложение",
                "type": "19"
            }
        ]
    },
    "1736728": {
        "playerItemId": "1736728",
        "buddyItemId": "",
        "replica": {
            "baseRecord": "records\/items\/gearweapons\/guns1h\/a10_gun1h002.dbr",
            "prefixRecord": "records\/items\/lootaffixes\/prefix\/b_wpn012_melee1h_d.dbr",
            "suffixRecord": "records\/items\/lootaffixes\/suffix\/a016a_ch_speedcast_03_we.dbr",
            "modifierRecord": "",
            "transmuteRecord": "",
            "seed": "156767928",
            "materiaRecord": "",
            "relicBonus": "",
            "relicSeed": "0",
            "enchantmentRecord": "",
            "enchantmentSeed": "0"
        },
        "stats": [
            {
                "text": "^gразрядный ^sимперский ^Wсемиствольник ^yсмекалки",
                "type": "4"
            },
            {
                "text": "Редкий пистолет",
                "type": "64"
            },
            {
                "text": "19-92 ^Kфизического урона^S",
                "type": "17"
            },
            {
                "text": "100% ^Sпробивание брони",
                "type": "17"
            },
            {
                "text": "^W1.57 ^Sатак в сек.",
                "type": "19"
            },
            {
                "text": " ",
                "type": "0"
            },
            {
                "text": "1-15 ^Zурона молнией^E",
                "type": "18"
            },
            {
                "text": "+35% ^Zурона молнией^E",
                "type": "18"
            },
            {
                "text": "13% конверсия: ^E^Kфизический урон^E в ^Zурон молнией^E",
                "type": "18"
            },
            {
                "text": "+36 ^Xнавыка атаки^E",
                "type": "18"
            },
            {
                "text": "+22% ^Xскорости колдовства^E",
                "type": "18"
            },
            {
                "text": "+2 к умению Дикость (Шаман)",
                "type": "79"
            },
            {
                "text": " ",
                "type": "0"
            },
            {
                "text": "Дарованные умения",
                "type": "34"
            },
            {
                "text": "Стрела молнии (10% шанс при атаке)",
                "type": "35"
            },
            {
                "text": "Чистая молния ударяет в вашу цель.",
                "type": "37"
            },
            {
                "text": " ",
                "type": "0"
            },
            {
                "text": "2.5 ^Eсек. ^Eперезарядка умения",
                "type": "18"
            },
            {
                "text": "1 ^Eм целевая область",
                "type": "18"
            },
            {
                "text": "287-1394 ^Zурона молнией^E",
                "type": "18"
            },
            {
                "text": "722 ^Zэлектрошока^E ^Eза ^H2 ^Eсек.",
                "type": "18"
            },
            {
                "text": "^Eоглушение ^Eна ^H0.5 - 1 ^Eсек.",
                "type": "18"
            },
            {
                "text": " ",
                "type": "0"
            },
            {
                "text": "Нужно: 55 Уровень игрока",
                "type": "19"
            },
            {
                "text": "Нужно: 399 Искусность",
                "type": "19"
            }
        ]
    }
}
