{
    "360571": {
        "playerItemId": "360571",
        "buddyItemId": "",
        "replica": {
            "baseRecord": "records\/items\/gearweapons\/guns1h\/c012_gun1h.dbr",
            "prefixRecord": "",
            "suffixRecord": "",
            "modifierRecord": "",
            "transmuteRecord": "",
            "seed": "127007484",
            "materiaRecord": "",
            "relicBonus": "",
            "relicSeed": "0",
            "enchantmentRecord": "",
            "enchantmentSeed": "0"
        },
        "stats": [
            {
                "text": "^Bчумной револьвер",
                "type": "5"
            },
            {
                "text": "Эпический пистолет",
                "type": "64"
            },
            {
                "text": "15-32 ^Lурона кислотой^S",
                "type": "17"
            },
            {
                "text": "^W1.68 ^Sатак в сек.",
                "type": "19"
            },
            {
                "text": " ",
                "type": "0"
            },
            {
                "text": "185 ^Lяда^E ^Eза ^H5 ^Eсек.",
                "type": "18"
            },
            {
                "text": "+67% ^Lурона ядом^E",
                "type": "18"
            },
            {
                "text": "+40 ^Fдуха^E",
                "type": "18"
            },
            {
                "text": "-4% ^Eвремени перезарядки умения",
                "type": "18"
            },
            {
                "text": "+1 к умениям мастерства Оккультист",
                "type": "79"
            },
            {
                "text": " ",
                "type": "0"
            },
            {
                "text": "Дарованные умения",
                "type": "34"
            },
            {
                "text": "Кровавая оспа (33% шанс при получении удара)",
                "type": "35"
            },
            {
                "text": "Отвратительное проклятие призывает свирепую заразу, распространяющуюся среди ваших врагов.",
                "type": "37"
            },
            {
                "text": " ",
                "type": "0"
            },
            {
                "text": "3 ^Eсек. ^Eперезарядка умения",
                "type": "18"
            },
            {
                "text": "6 ^Eсек. длительность",
                "type": "18"
            },
            {
                "text": "^Eснижение здоровья на ^H4-6%",
                "type": "18"
            },
            {
                "text": "91 ^Rкровотечения^E в сек.",
                "type": "18"
            },
            {
                "text": " ",
                "type": "0"
            },
            {
                "text": "^rНужно: Уровень игрока: 46",
                "type": "19"
            },
            {
                "text": "^rНужно: 297 Искусность [^y- 9% от ^r326]",
                "type": "19"
            }
        ]
    }
}
